{
  "place_id": "ChIJc3D8SX2UC0cR0w7pGtniUw8",
  "geometry": {
    "location_type": "ROOFTOP",
    "viewport": {
      "northeast": {
        "lng": 14.4363752802915,
        "lat": 50.06874268029149
      },
      "southwest": {
        "lng": 14.4336773197085,
        "lat": 50.0660447197085
      }
    },
    "location": {
      "lng": 14.4350263,
      "lat": 50.0673937
    }
  },
  "types": [
    "street_address"
  ],
  "address_components": [
    {
      "long_name": "25",
      "types": [
        "street_number"
      ],
      "short_name": "25"
    },
    {
      "long_name": "1690",
      "types": [
        "premise"
      ],
      "short_name": "1690"
    },
    {
      "long_name": "Sarajevská",
      "types": [
        "route"
      ],
      "short_name": "Sarajevská"
    },
    {
      "long_name": "Vinohrady",
      "types": [
        "neighborhood",
        "political"
      ],
      "short_name": "Vinohrady"
    },
    {
      "long_name": "Praha 2",
      "types": [
        "political",
        "sublocality",
        "sublocality_level_1"
      ],
      "short_name": "Praha 2"
    },
    {
      "long_name": "Hlavní město Praha",
      "types": [
        "administrative_area_level_2",
        "political"
      ],
      "short_name": "Hlavní město Praha"
    },
    {
      "long_name": "Hlavní město Praha",
      "types": [
        "administrative_area_level_1",
        "political"
      ],
      "short_name": "Hlavní město Praha"
    },
    {
      "long_name": "Czechia",
      "types": [
        "country",
        "political"
      ],
      "short_name": "CZ"
    },
    {
      "long_name": "120 00",
      "types": [
        "postal_code"
      ],
      "short_name": "120 00"
    }
  ],
  "formatted_address": "Sarajevská 1690/25, 120 00 Praha 2-Vinohrady, Czechia"
}